asynctradier/__init__.py
asynctradier/clients/__init__.py
asynctradier/clients/account_clients.py
asynctradier/clients/marketdata_client.py
asynctradier/clients/streaming_client.py
asynctradier/clients/trading_client.py
asynctradier/clients/watchlist_client.py
asynctradier/common/__init__.py
asynctradier/common/account_balance.py
asynctradier/common/calendar.py
asynctradier/common/clock.py
asynctradier/common/event.py
asynctradier/common/expiration.py
asynctradier/common/gain_loss.py
asynctradier/common/market_data.py
asynctradier/common/option_contract.py
asynctradier/common/order.py
asynctradier/common/position.py
asynctradier/common/quote.py
asynctradier/common/security.py
asynctradier/common/user_profile.py
asynctradier/common/watchlist.py
asynctradier/exceptions/__init__.py
asynctradier/tradier.py
asynctradier/utils/__init__.py
asynctradier/utils/common.py
asynctradier/utils/webutils.py
asynctradier-1.0.0.dist-info/WHEEL
asynctradier-1.0.0.dist-info/LICENSE
asynctradier-1.0.0.dist-info/METADATA
asynctradier-1.0.0.dist-info/RECORD
