Metadata-Version: 2.1
Name: asynctradier
Version: 1.0.0
Summary: Async api wrapper for [Tradier](https://documentation.tradier.com/).
Author: Jiakuan Li
Author-email: jiakuan.li.cs@gmail.com
Requires-Python: >=3.9,<4.0
Classifier: Programming Language :: Python :: 3
Classifier: Programming Language :: Python :: 3.9
Classifier: Programming Language :: Python :: 3.10
Classifier: Programming Language :: Python :: 3.11
Requires-Dist: aiohttp (>=3.9.5,<4.0.0)
Requires-Dist: strenum (>=0.4.15,<0.5.0)
Requires-Dist: websockets (>=12.0,<13.0)
